System_/__init__.py
_dafny/__init__.py
DafnyRuntimePython-4.9.1.dist-info/METADATA
DafnyRuntimePython-4.9.1.dist-info/WHEEL
DafnyRuntimePython-4.9.1.dist-info/top_level.txt
DafnyRuntimePython-4.9.1.dist-info/RECORD
